langroid_client/__init__.py
langroid_client/client.py
langroid_client-0.1.10.dist-info/METADATA
langroid_client-0.1.10.dist-info/WHEEL
langroid_client-0.1.10.dist-info/RECORD
