Metadata-Version: 2.1
Name: langroid-client
Version: 0.1.10
Summary: 
Author: Prasad Chalasani
Author-email: pchalasani@gmail.com
Requires-Python: >=3.11,<3.12
Classifier: Programming Language :: Python :: 3
Classifier: Programming Language :: Python :: 3.11
Requires-Dist: pydantic (>=2.6.3,<3.0.0)
Requires-Dist: pytest (>=8.0.2,<9.0.0)
Requires-Dist: python-dotenv (>=1.0.1,<2.0.0)
Requires-Dist: requests (>=2.31.0,<3.0.0)
